myspeed/__init__.py
myspeed/myspeed.py
myspeed-0.0.3.dist-info/LICENSE
myspeed-0.0.3.dist-info/METADATA
myspeed-0.0.3.dist-info/WHEEL
myspeed-0.0.3.dist-info/entry_points.txt
myspeed-0.0.3.dist-info/top_level.txt
myspeed-0.0.3.dist-info/RECORD
