Metadata-Version: 2.1
Name: myspeed
Version: 0.0.3
Summary: SIMPLE INTERNET SPEED TESTING TOOL.
Home-page: https://github.com/TOXIC-SOUL
Author: AKXVAU
Author-email: akxvau@gmail.com
License: MIT
Keywords: hacker,spam,tool,sms,bomber,call,prank,termux,hack,sms bomber,sms bomber,AKXVAU,TOXIC-VIRUS,TOXIC-SOUL,INTERNET SPEED,SPEED TEST,INTERNET
Platform: UNKNOWN
Classifier: Development Status :: 4 - Beta
Classifier: Intended Audience :: Developers
Classifier: Topic :: Software Development :: Libraries :: Python Modules
Classifier: License :: OSI Approved :: MIT License
Classifier: Programming Language :: Python :: 3
Classifier: Operating System :: OS Independent
Classifier: Environment :: Console
Requires-Python: >=3.9
License-File: LICENSE
Requires-Dist: lolcat
